LICENSE
MANIFEST.in
README.md
setup.py
sentry_extras/__init__.py
sentry_extras/filters.py
sentry_extras/plugin.py
sentry_extras.egg-info/PKG-INFO
sentry_extras.egg-info/SOURCES.txt
sentry_extras.egg-info/dependency_links.txt
sentry_extras.egg-info/entry_points.txt
sentry_extras.egg-info/not-zip-safe
sentry_extras.egg-info/requires.txt
sentry_extras.egg-info/top_level.txt