Metadata-Version: 1.0
Name: sentry-extras
Version: 0.0.4
Summary: Some useful extras for Sentry
Home-page: http://github.com/davidszotten/sentry-extras
Author: David Szotten
Author-email: Author name (as one word) at gmail.com
License: MIT
Platform: UNKNOWN
